<mockup version="4.2" platform="MtMobile" defaultW="375" defaultH="667" from="FmLocal" screenOrientation="MoPortrait" mobileScreenScale="1.77777779102325" minAllowVersion="4.1" ID="4C418FC0-C696-E611-84ED-68A86D1373AA" measureW="375" measureH="667" clipArea="(0,0,0,0)">
  <controls controlCount="6">
    <control controlID="C4C311CB-C696-E611-84ED-68A86D1373AA" controlTypeID="Image" isShow="True" caption="%E5%9B%BE%E7%89%87" x="0" y="65" w="375" h="602" measuredW="150" measuredH="150" zOrder="0" locked="False" sizeLocked="False">
      <controlProperties>
        <basic color="4294967295" borderVisible="False" borderColor="4284900966" isAutoSize="False" status="MsEnabled" opacity="1" isCommentCom="False" canMove="True" alias="" rotation="0"/>
        <states/>
        <verticalScrollbarShow>False</verticalScrollbarShow>
        <verticalScrollbarProgress>0</verticalScrollbarProgress>
        <horizontalScrollbarShow>False</horizontalScrollbarShow>
        <horizontalScrollbarProgress>0</horizontalScrollbarProgress>
        <links eventType="AtClick" animate="AmNone" animateAutoDelay="0" animateDuration="500">
          <link targetPageID="" linkType="ltPageLink" isApplyIncludePage="False" title="%E9%93%BE%E6%8E%A5">
            <area shape="0" alt="" ID="{10C811CB-C696-E611-84ED-68A86D1373AA}" coords="(0,0,375,602)"/>
          </link>
        </links>
        <interactiveData>
          <entry title="">
            <area shape="0" alt="" ID="{1EC911CB-C696-E611-84ED-68A86D1373AA}" coords="(0,0,375,602)"/>
            <events title=""/>
          </entry>
        </interactiveData>
        <rotationAngle>TdZero</rotationAngle>
        <clipShapeType>SbRectangle</clipShapeType>
        <radius>0</radius>
        <radiusIsPercent>False</radiusIsPercent>
        <filterType>MfNone</filterType>
        <filterPencilValue>2</filterPencilValue>
        <filterSketchValue>5</filterSketchValue>
        <URL>CB8DE8660D18E6CB5F7587DB34621FAA.png</URL>
        <FlipHorizontal>False</FlipHorizontal>
        <FlipVertical>False</FlipVertical>
        <fitMode>2</fitMode>
      </controlProperties>
    </control>
    <control controlID="DC542BE5-C696-E611-84ED-68A86D1373AA" controlTypeID="Image" isShow="True" caption="%E5%9B%BE%E7%89%87" x="0" y="0" w="375" h="65" measuredW="150" measuredH="150" zOrder="1" locked="False" sizeLocked="False">
      <controlProperties>
        <basic color="4294967295" borderVisible="False" borderColor="4284900966" isAutoSize="False" status="MsEnabled" opacity="1" isCommentCom="False" canMove="True" alias="" rotation="0"/>
        <states/>
        <verticalScrollbarShow>False</verticalScrollbarShow>
        <verticalScrollbarProgress>0</verticalScrollbarProgress>
        <horizontalScrollbarShow>False</horizontalScrollbarShow>
        <horizontalScrollbarProgress>0</horizontalScrollbarProgress>
        <links eventType="AtClick" animate="AmNone" animateAutoDelay="0" animateDuration="500">
          <link targetPageID="76C3B777-E195-E611-94F5-68A86D1373AA" linkType="ltPageLink" isApplyIncludePage="False" title="%E9%A6%96%E9%A1%B5">
            <area shape="0" alt="" ID="{84572BE5-C696-E611-84ED-68A86D1373AA}" coords="(0,0,375,65)"/>
          </link>
        </links>
        <interactiveData>
          <entry title="">
            <area shape="0" alt="" ID="{1A582BE5-C696-E611-84ED-68A86D1373AA}" coords="(0,0,375,65)"/>
            <events title=""/>
          </entry>
        </interactiveData>
        <rotationAngle>TdZero</rotationAngle>
        <clipShapeType>SbRectangle</clipShapeType>
        <radius>0</radius>
        <radiusIsPercent>False</radiusIsPercent>
        <filterType>MfNone</filterType>
        <filterPencilValue>2</filterPencilValue>
        <filterSketchValue>5</filterSketchValue>
        <URL>ED050722C4FDDCBEA7034C5512EA0CE8.png</URL>
        <FlipHorizontal>False</FlipHorizontal>
        <FlipVertical>False</FlipVertical>
        <fitMode>2</fitMode>
      </controlProperties>
    </control>
    <control controlID="8A07CEEB-C696-E611-84ED-68A86D1373AA" controlTypeID="Image" isShow="True" caption="%E5%9B%BE%E7%89%87" x="22" y="189" w="331" h="151" measuredW="150" measuredH="150" zOrder="2" locked="False" sizeLocked="False">
      <controlProperties>
        <basic color="4294967295" borderVisible="False" borderColor="4284900966" isAutoSize="False" status="MsEnabled" opacity="1" isCommentCom="False" canMove="True" alias="" rotation="0"/>
        <states/>
        <verticalScrollbarShow>False</verticalScrollbarShow>
        <verticalScrollbarProgress>0</verticalScrollbarProgress>
        <horizontalScrollbarShow>False</horizontalScrollbarShow>
        <horizontalScrollbarProgress>0</horizontalScrollbarProgress>
        <links eventType="AtClick" animate="AmNone" animateAutoDelay="0" animateDuration="500">
          <link targetPageID="" linkType="ltPageLink" isApplyIncludePage="False" title="%E9%93%BE%E6%8E%A5">
            <area shape="0" alt="" ID="{D20ACEEB-C696-E611-84ED-68A86D1373AA}" coords="(0,0,331,151)"/>
          </link>
        </links>
        <interactiveData>
          <entry title="">
            <area shape="0" alt="" ID="{9A0BCEEB-C696-E611-84ED-68A86D1373AA}" coords="(0,0,331,151)"/>
            <events title=""/>
          </entry>
        </interactiveData>
        <rotationAngle>TdZero</rotationAngle>
        <clipShapeType>SbRectangle</clipShapeType>
        <radius>0</radius>
        <radiusIsPercent>False</radiusIsPercent>
        <filterType>MfNone</filterType>
        <filterPencilValue>2</filterPencilValue>
        <filterSketchValue>5</filterSketchValue>
        <URL>931D50A202A30AAB2E00116D069D9D52.png</URL>
        <FlipHorizontal>False</FlipHorizontal>
        <FlipVertical>False</FlipVertical>
        <fitMode>2</fitMode>
      </controlProperties>
    </control>
    <control controlID="7C320BFB-C696-E611-84ED-68A86D1373AA" controlTypeID="Image" isShow="True" caption="%E5%9B%BE%E7%89%87" x="22" y="75" w="331" h="114" measuredW="150" measuredH="150" zOrder="3" locked="False" sizeLocked="False">
      <controlProperties>
        <basic color="4294967295" borderVisible="False" borderColor="4284900966" isAutoSize="False" status="MsEnabled" opacity="1" isCommentCom="False" canMove="True" alias="" rotation="0"/>
        <states/>
        <verticalScrollbarShow>False</verticalScrollbarShow>
        <verticalScrollbarProgress>0</verticalScrollbarProgress>
        <horizontalScrollbarShow>False</horizontalScrollbarShow>
        <horizontalScrollbarProgress>0</horizontalScrollbarProgress>
        <links eventType="AtClick" animate="AmNone" animateAutoDelay="0" animateDuration="500">
          <link targetPageID="F433498C-C996-E611-84ED-68A86D1373AA" linkType="ltPageLink" isApplyIncludePage="False" title="%E7%BB%BC%E5%90%88%E6%8C%87%E6%A0%87">
            <area shape="0" alt="" ID="{14360BFB-C696-E611-84ED-68A86D1373AA}" coords="(0,0,331,114)"/>
          </link>
        </links>
        <interactiveData>
          <entry title="">
            <area shape="0" alt="" ID="{DC360BFB-C696-E611-84ED-68A86D1373AA}" coords="(0,0,331,114)"/>
            <events title=""/>
          </entry>
        </interactiveData>
        <rotationAngle>TdZero</rotationAngle>
        <clipShapeType>SbRectangle</clipShapeType>
        <radius>0</radius>
        <radiusIsPercent>False</radiusIsPercent>
        <filterType>MfNone</filterType>
        <filterPencilValue>2</filterPencilValue>
        <filterSketchValue>5</filterSketchValue>
        <URL>AA4EAEABAD1F79633938FDAE3218F228.png</URL>
        <FlipHorizontal>False</FlipHorizontal>
        <FlipVertical>False</FlipVertical>
        <fitMode>2</fitMode>
      </controlProperties>
    </control>
    <control controlID="306FF141-C796-E611-84ED-68A86D1373AA" controlTypeID="Image" isShow="True" caption="%E5%9B%BE%E7%89%87" x="22" y="340" w="331" h="50" measuredW="150" measuredH="150" zOrder="4" locked="False" sizeLocked="False">
      <controlProperties>
        <basic color="4294967295" borderVisible="False" borderColor="4284900966" isAutoSize="False" status="MsEnabled" opacity="1" isCommentCom="False" canMove="True" alias="" rotation="0"/>
        <states/>
        <verticalScrollbarShow>False</verticalScrollbarShow>
        <verticalScrollbarProgress>0</verticalScrollbarProgress>
        <horizontalScrollbarShow>False</horizontalScrollbarShow>
        <horizontalScrollbarProgress>0</horizontalScrollbarProgress>
        <links eventType="AtClick" animate="AmNone" animateAutoDelay="0" animateDuration="500">
          <link targetPageID="" linkType="ltPageLink" isApplyIncludePage="False" title="%E9%93%BE%E6%8E%A5">
            <area shape="0" alt="" ID="{6472F141-C796-E611-84ED-68A86D1373AA}" coords="(0,0,331,50)"/>
          </link>
        </links>
        <interactiveData>
          <entry title="">
            <area shape="0" alt="" ID="{1873F141-C796-E611-84ED-68A86D1373AA}" coords="(0,0,331,50)"/>
            <events title=""/>
          </entry>
        </interactiveData>
        <rotationAngle>TdZero</rotationAngle>
        <clipShapeType>SbRectangle</clipShapeType>
        <radius>0</radius>
        <radiusIsPercent>False</radiusIsPercent>
        <filterType>MfNone</filterType>
        <filterPencilValue>2</filterPencilValue>
        <filterSketchValue>5</filterSketchValue>
        <URL>D8B6DED918F7722DF64686D681EEBD93.png</URL>
        <FlipHorizontal>False</FlipHorizontal>
        <FlipVertical>False</FlipVertical>
        <fitMode>2</fitMode>
      </controlProperties>
    </control>
    <control controlID="EC4CB95D-C796-E611-84ED-68A86D1373AA" controlTypeID="Image" isShow="True" caption="%E5%9B%BE%E7%89%87" x="22" y="390" w="331" h="257" measuredW="150" measuredH="150" zOrder="5" locked="False" sizeLocked="False">
      <controlProperties>
        <basic color="4294967295" borderVisible="False" borderColor="4284900966" isAutoSize="False" status="MsEnabled" opacity="1" isCommentCom="False" canMove="True" alias="" rotation="0"/>
        <states/>
        <verticalScrollbarShow>False</verticalScrollbarShow>
        <verticalScrollbarProgress>0</verticalScrollbarProgress>
        <horizontalScrollbarShow>False</horizontalScrollbarShow>
        <horizontalScrollbarProgress>0</horizontalScrollbarProgress>
        <links eventType="AtClick" animate="AmNone" animateAutoDelay="0" animateDuration="500">
          <link targetPageID="1C598A40-C896-E611-84ED-68A86D1373AA" linkType="ltPageLink" isApplyIncludePage="False" title="%E6%88%91%E7%9A%84%E8%AF%84%E5%88%86">
            <area shape="0" alt="" ID="{0250B95D-C796-E611-84ED-68A86D1373AA}" coords="(0,0,331,257)"/>
          </link>
        </links>
        <interactiveData>
          <entry title="">
            <area shape="0" alt="" ID="{C050B95D-C796-E611-84ED-68A86D1373AA}" coords="(0,0,331,257)"/>
            <events title=""/>
          </entry>
        </interactiveData>
        <rotationAngle>TdZero</rotationAngle>
        <clipShapeType>SbRectangle</clipShapeType>
        <radius>0</radius>
        <radiusIsPercent>False</radiusIsPercent>
        <filterType>MfNone</filterType>
        <filterPencilValue>2</filterPencilValue>
        <filterSketchValue>5</filterSketchValue>
        <URL>98FAE145BCFAE1DC2629773AF4904B86.png</URL>
        <FlipHorizontal>False</FlipHorizontal>
        <FlipVertical>False</FlipVertical>
        <fitMode>2</fitMode>
      </controlProperties>
    </control>
  </controls>
  <param>
    <backgroundColor>4294967295</backgroundColor>
    <fontFamily/>
    <guideLines/>
  </param>
</mockup>